fastapi_header_version/__init__.py
fastapi_header_version/app.py
fastapi_header_version/helpers.py
fastapi_header_version/router.py
fastapi_header_version/types.py
fastapi_header_versions-0.2.2.dist-info/METADATA
fastapi_header_versions-0.2.2.dist-info/WHEEL
fastapi_header_versions-0.2.2.dist-info/top_level.txt
fastapi_header_versions-0.2.2.dist-info/RECORD
