Metadata-Version: 2.4
Name: fastapi-header-versions
Version: 0.2.2
Summary: Fastapi versioning package with accept header
Project-URL: repository, https://github.com/mxnoob/fastapi-header-versions
Requires-Python: >=3.12
Requires-Dist: fastapi>=0.100
